mutil/__init__.py
mutil/minduct.py
mutil/mutil.py
mutil/version.py
mutil-0.4.0.dist-info/LICENSE
mutil-0.4.0.dist-info/METADATA
mutil-0.4.0.dist-info/WHEEL
mutil-0.4.0.dist-info/entry_points.txt
mutil-0.4.0.dist-info/top_level.txt
mutil-0.4.0.dist-info/RECORD
