Metadata-Version: 2.1
Name: mutil
Version: 0.4.0
Summary: Utility for managing memory with cgroup
Author-email: Anthony Aylward <aaylward@salk.edu>
Project-URL: Homepage, https://gitlab.com/salk-tm/mutil
Project-URL: Documentation, https://salk-tm.gitlab.io/mutil
Classifier: Programming Language :: Python :: 3
Classifier: License :: OSI Approved :: MIT License
Classifier: Operating System :: OS Independent
Requires-Python: >=3.7
License-File: LICENSE
Requires-Dist: psutil
